[{"name":"@pokemongojiang","tweets":[{"id":"1440558891041837064","text":"[更新]\n\n親愛的訓練家們：\n\n關於昨日時裝週活動－挑戰者的圖文\n已新增時尚挑戰者頭像與相對應的陣容小隊\n如因內容標題與排版不周博士深感歉意\n\n⚠️時尚挑戰者將於時裝週活動期間隨機出現在寶可補給站，挑戰他們成功便能獲得星星沙子和道具獎勵\n\n祝各位好運！J\n\n#FashionWeek #FashionableChallenger https://t.co/PKCUnxGCX0 https://t.co/RwCj7qsw1C","mediaList":[{"url":"https://pbs.twimg.com/media/E_3kV6dVIAY6jBR.jpg","media_key":"3_1440558520949088262","width":4096,"height":4096,"type":"photo"}],"createdAt":"2021-09-22T06:09:38.000Z"},{"id":"1440194827547676681","text":"親愛的訓練家們：\n\n在時裝週活動舉行之際\n活動田野調查與挑戰者將同步登場\n\n活動時間：2021年9月21日10:00 至 2021年9月28日20:00 (Local)\n\n祝各位好運！J\n\n#PokemonGO #FashionWeek #FieldResearch https://t.co/hFraCKk4Aj","mediaList":[{"url":"https://pbs.twimg.com/media/E_yZigaVcAM8Tf6.jpg","media_key":"3_1440194798946709507","width":4096,"height":4096,"type":"photo"}],"createdAt":"2021-09-21T06:02:59.000Z"},{"id":"1440128653350739968","text":"親愛的訓練家們：\n\n擺好姿勢📸\n和各式扮裝的寶可夢一同演繹時髦風格吧！\n\n活動名稱：時裝週\n活動時間：2021年9月21日10:00 至 2021年9月28日20:00 (Local)\n\n⚠️活動田野調查將於今日稍晚附上\n⚠️有機會遇見初次登場的多麗米亞\n⚠️有機會遇見異色的扮裝寶可夢✨\n\n祝各位好運！J\n\n#PokemonGO #FashionWeek https://t.co/fCfdCNoUom","mediaList":[{"url":"https://pbs.twimg.com/media/E_xdFDeVkAIf_Rp.jpg","media_key":"3_1440128322264993794","width":2304,"height":4096,"type":"photo"}],"createdAt":"2021-09-21T01:40:01.000Z"},{"id":"1440115281691430917","text":"親愛的訓練家們：\n\n以 #美洛耶塔 為靈感的特殊調查即刻起登場\n\n調查名稱：尋覓你的歌聲\n開始時間：2021年9月21日10:00 (Local)\n\n⚠️所有訓練家皆能領取此特殊調查\n⚠️如先前已捕捉過美洛耶塔獎勵改為其糖果\n⚠️特殊調查毋時間限制，可依自己步調完成\n\n祝各位好運！J\n\n#PokemonGO #Meloetta https://t.co/IT5yrhpsh1","mediaList":[{"url":"https://pbs.twimg.com/media/E_xRMaLVkAAg422.jpg","media_key":"3_1440115254478868480","width":2194,"height":4096,"type":"photo"}],"createdAt":"2021-09-21T00:46:53.000Z"},{"id":"1440074938384224272","text":"親愛的訓練家們：\n\n在時裝週活動舉行之際\n遊戲內將同步舉辦限時調查\n\n調查名稱：時裝週\n活動時間：2021年9月21日10:00 至 2021年9月28日20:00 (Local)\n\n⚠️限時調查將出現在「今天」標籤頁\n⚠️活動結束時調查與獎勵將自動消失\n\n祝各位好運！J\n\n#PokemonGO #FashionWeek https://t.co/ClfkcXhF1S","mediaList":[{"url":"https://pbs.twimg.com/media/E_wsg0lVEAMpyXV.jpg","media_key":"3_1440074923234365443","width":2483,"height":4096,"type":"photo"}],"createdAt":"2021-09-20T22:06:35.000Z"},{"id":"1440047735986556931","text":"親愛的訓練家們：\n\n繼續探索本季節特殊調查的下一階段故事吧！\n\n調查名稱：不被理解的光怪陸離\n進度版本：2021年9月21日10:00 (Local) 開始\n\n⚠️此特殊調查關卡將會逐步開放\n⚠️下一階段開放時間為2021年10月初\n⚠️完成此調查你將能在日後參加一場特殊活動\n\n祝各位好運！J \n\n#PokemonGO https://t.co/f0UUX7ZLG5","mediaList":[{"url":"https://pbs.twimg.com/media/E_wTv0lUcAEstPY.jpg","media_key":"3_1440047693141667841","width":2876,"height":4096,"type":"photo"},{"url":"https://pbs.twimg.com/media/E_wTxh5UUAcK_Wj.jpg","media_key":"3_1440047722485010439","width":2876,"height":4096,"type":"photo"}],"createdAt":"2021-09-20T20:18:29.000Z"},{"id":"1439802826893320194","text":"親愛的訓練家們：\n\n一起來參與本週的活動吧！\n活動名稱：寶可夢聚焦時刻 #向尾喵\n活動日期：2021年9月21日18:00 至 19:00 (Local)\n\n⚠️幸運的話有機會遇見異色✨向尾喵✨\n⚠️捕捉寶可夢獲得的糖果加倍🍬\n\n祝各位好運！J\n\n#PokemonGO #SpotlightHour #Skitty https://t.co/r0xBjnFEI7","mediaList":[{"url":"https://pbs.twimg.com/media/E_s07JbVkAUlWix.jpg","media_key":"3_1439802696622510085","width":4096,"height":4096,"type":"photo"}],"createdAt":"2021-09-20T04:05:18.000Z"},{"id":"1439802453231239174","text":"親愛的臺灣訓練家們：\n\n一起來捕捉寶可夢，為你的城市挺身而戰！\n活動名稱：全島糖王爭霸戰\n活動時間：2021年9月21日08:00 至 2021年9月28日20:00 (GMT+8)\n\n⚠️此活動僅適用於臺灣(不含離島)\n⚠️活動開始時查看排行榜👉https://t.co/eN80l4RPN3\n\n哪個城市能成為首屆全島糖王呢？J\n\n#PokemonGO #Taiwan https://t.co/trAWJgdHwo","mediaList":[{"url":"https://pbs.twimg.com/media/E_s0rOlVQAAem18.jpg","media_key":"3_1439802423128702976","width":4096,"height":4096,"type":"photo"}],"createdAt":"2021-09-20T04:03:49.000Z"},{"id":"1439620637958443023","text":"親愛的訓練家們：\n\n本週的1寶可幣禮盒即將登場\n上架日期：2021年9月20日06:00 至 2021年9月27日06:00 (Local) \n\n⚠️禮盒需用1枚寶可幣交換\n⚠️每位訓練家僅限購買1次\n⚠️購買時，請確認包包裡的遠距團體戰入場券數量必須少於3張\n\n千萬別錯過！J\n\n#PokemonGO #1PokéCoinBundle https://t.co/A1CmtKAMYP","mediaList":[{"url":"https://pbs.twimg.com/media/E_qPUCpVQAIlcKJ.jpg","media_key":"3_1439620605368680450","width":4096,"height":4096,"type":"photo"}],"createdAt":"2021-09-19T16:01:21.000Z"},{"id":"1439336316001406977","text":"親愛的訓練家們：\n\n與你們分享 #水水獺 社群日特殊調查的內容\n調查名稱：從扇貝貝到足刃\n開始時間：2021年9月19日11:00 (Local)\n⚠️需購買入場券才能獲得特殊調查\n⚠️特殊調查毋時間限制，可依自己步調完成調查\n⚠️確保最佳遊戲體驗，建議在活動期間完成調查\n\n祝各位好運！J\n\n#PokemonGOCommunityDay https://t.co/DK5N9BB6P8","mediaList":[{"url":"https://pbs.twimg.com/media/E_mMuaSVcAAjLl1.jpg","media_key":"3_1439336284879679488","width":4096,"height":4096,"type":"photo"}],"createdAt":"2021-09-18T21:11:33.000Z"}]}]